{"station":[{"id":"polska","name":"Polska","plug_name":"RMF MAXX Polska","stream":"https://rs101-krk-cyfronet.rmfstream.pl/rmf_maxxx","playlist":"getNowPlayingGrupaRMF(6);","station_schedule":"polska","cover":"https://i.ibb.co/wZWkL29X/RMF-MAXX-logo.jpg"},{"id":"bydgoszcz","name":"Bydgoszcz","plug_name":"RMF MAXX Bydgoszcz","stream":"https://rs103-krk.rmfstream.pl/rmf_maxxx_byd","playlist":"getNowPlayingGrupaRMF(6);","station_schedule":"bydgoszcz","cover":"https://i.ibb.co/wZWkL29X/RMF-MAXX-logo.jpg"},{"id":"mazowsze","name":"Mazowsze","plug_name":"RMF MAXX Mazowsze","stream":"https://rs103-krk-cyfronet.rmfstream.pl/rmf_maxxx_cie","playlist":"getNowPlayingGrupaRMF(6);","station_schedule":"mazowsze","cover":"https://i.ibb.co/wZWkL29X/RMF-MAXX-logo.jpg"},{"id":"czestochowa","name":"Częstochowa","plug_name":"RMF MAXX Częstochowa","stream":"https://rs203-krk-cyfronet.rmfstream.pl/rmf_maxxx_cze","playlist":"getNowPlayingGrupaRMF(6);","station_schedule":"czestochowa","cover":"https://i.ibb.co/wZWkL29X/RMF-MAXX-logo.jpg"},{"id":"trojmiasto","name":"Trójmiasto","plug_name":"RMF MAXX Trójmiasto","stream":"https://rs103-krk.rmfstream.pl/rmf_maxxx_gda","playlist":"getNowPlayingGrupaRMF(6);","station_schedule":"trojmiasto","cover":"https://i.ibb.co/wZWkL29X/RMF-MAXX-logo.jpg"},{"id":"inowroclaw","name":"Inowrocław","plug_name":"RMF MAXX Inowrocław","stream":"https://rs101-krk.rmfstream.pl/rmf_maxxx_ino","playlist":"getNowPlayingGrupaRMF(6);","station_schedule":"inowroclaw","cover":"https://i.ibb.co/wZWkL29X/RMF-MAXX-logo.jpg"},{"id":"swietokrzyskie","name":"Świętokrzyskie","plug_name":"RMF MAXX Świętokrzyskie","stream":"https://rs202-krk-cyfronet.rmfstream.pl/rmf_maxxx_kie","playlist":"getNowPlayingGrupaRMF(6);","station_schedule":"swietokrzyskie","cover":"https://i.ibb.co/wZWkL29X/RMF-MAXX-logo.jpg"},{"id":"konin","name":"Konin","plug_name":"RMF MAXX Konin","stream":"https://rs203-krk.rmfstream.pl/rmf_maxxx_knn","playlist":"getNowPlayingGrupaRMF(6);","station_schedule":"konin","cover":"https://i.ibb.co/wZWkL29X/RMF-MAXX-logo.jpg"},{"id":"krakow","name":"Kraków","plug_name":"RMF MAXX Kraków","stream":"https://rs101-krk.rmfstream.pl/rmf_maxxx_kra","playlist":"getNowPlayingGrupaRMF(6);","station_schedule":"krakow","cover":"https://i.ibb.co/wZWkL29X/RMF-MAXX-logo.jpg"},{"id":"krosno","name":"Krosno","plug_name":"RMF MAXX Krosno","stream":"https://rs103-krk.rmfstream.pl/rmf_maxxx_ksn","playlist":"getNowPlayingGrupaRMF(6);","station_schedule":"krosno","cover":"https://i.ibb.co/wZWkL29X/RMF-MAXX-logo.jpg"},{"id":"podlasie","name":"Podlasie","plug_name":"RMF MAXX Podlasie","stream":"https://rs201-krk-cyfronet.rmfstream.pl/rmf_maxxx_lom","playlist":"getNowPlayingGrupaRMF(6);","station_schedule":"podlasie","cover":"https://i.ibb.co/wZWkL29X/RMF-MAXX-logo.jpg"},{"id":"nowy_sacz","name":"Nowy Sącz","plug_name":"RMF MAXX Nowy Sącz","stream":"https://rs202-krk.rmfstream.pl/rmf_maxxx_nsa","playlist":"getNowPlayingGrupaRMF(6);","station_schedule":"nowy_sacz","cover":"https://i.ibb.co/wZWkL29X/RMF-MAXX-logo.jpg"},{"id":"olesnica","name":"Oleśnica","plug_name":"RMF MAXX Oleśnica","stream":"https://rs102-krk-cyfronet.rmfstream.pl/rmf_maxxx_ole","playlist":"getNowPlayingGrupaRMF(6);","station_schedule":"olesnica","cover":"https://i.ibb.co/wZWkL29X/RMF-MAXX-logo.jpg"},{"id":"opole","name":"Opole","plug_name":"RMF MAXX Opole","stream":"https://rs101-krk.rmfstream.pl/rmf_maxxx_opo","playlist":"getNowPlayingGrupaRMF(6);","station_schedule":"opole","cover":"https://i.ibb.co/wZWkL29X/RMF-MAXX-logo.jpg"},{"id":"pila","name":"Piła","plug_name":"RMF MAXX Piła","stream":"https://rs203-krk.rmfstream.pl/rmf_maxxx_pil","playlist":"getNowPlayingGrupaRMF(6);","station_schedule":"pila","cover":"https://i.ibb.co/wZWkL29X/RMF-MAXX-logo.jpg"},{"id":"poznan","name":"Poznań","plug_name":"RMF MAXX Poznań","stream":"https://rs101-krk.rmfstream.pl/rmf_maxxx_poz","playlist":"getNowPlayingGrupaRMF(6);","station_schedule":"poznan","cover":"https://i.ibb.co/wZWkL29X/RMF-MAXX-logo.jpg"},{"id":"slask","name":"Śląsk","plug_name":"RMF MAXX Śląsk","stream":"https://rs101-krk-cyfronet.rmfstream.pl/rmf_maxxx_slk","playlist":"getNowPlayingGrupaRMF(6);","station_schedule":"slask","cover":"https://i.ibb.co/wZWkL29X/RMF-MAXX-logo.jpg"},{"id":"pomorze","name":"Pomorze","plug_name":"RMF MAXX Pomorze","stream":"https://rs103-krk-cyfronet.rmfstream.pl/rmf_maxxx_slu","playlist":"getNowPlayingGrupaRMF(6);","station_schedule":"pomorze","cover":"https://i.ibb.co/wZWkL29X/RMF-MAXX-logo.jpg"},{"id":"szczecin","name":"Szczecin","plug_name":"RMF MAXX Szczecin","stream":"https://rs103-krk.rmfstream.pl/rmf_maxxx_szc","playlist":"getNowPlayingGrupaRMF(6);","station_schedule":"szczecin","cover":"https://i.ibb.co/wZWkL29X/RMF-MAXX-logo.jpg"},{"id":"tomaszow_maz.","name":"Tomaszów Maz.","plug_name":"RMF MAXX Tomaszów Maz.","stream":"https://rs103-krk.rmfstream.pl/rmf_maxxx_tmz","playlist":"getNowPlayingGrupaRMF(6);","station_schedule":"tomaszow_maz.","cover":"https://i.ibb.co/wZWkL29X/RMF-MAXX-logo.jpg"},{"id":"dolny_slask","name":"Dolny Śląsk","plug_name":"RMF MAXX Dolny Śląsk","stream":"https://rs201-krk.rmfstream.pl/rmf_maxxx_wal","playlist":"getNowPlayingGrupaRMF(6);","station_schedule":"dolny_slask","cover":"https://i.ibb.co/wZWkL29X/RMF-MAXX-logo.jpg"},{"id":"warszawa","name":"Warszawa","plug_name":"RMF MAXX Warszawa","stream":"https://rs101-krk.rmfstream.pl/rmf_maxxx_waw","playlist":"getNowPlayingGrupaRMF(6);","station_schedule":"warszawa","cover":"https://i.ibb.co/wZWkL29X/RMF-MAXX-logo.jpg"},{"id":"wloclawek","name":"Włocławek","plug_name":"RMF MAXX Włocławek","stream":"https://rs101-krk-cyfronet.rmfstream.pl/rmf_maxxx_wlc","playlist":"getNowPlayingGrupaRMF(6);","station_schedule":"wloclawek","cover":"https://i.ibb.co/wZWkL29X/RMF-MAXX-logo.jpg"},{"id":"lubuskie","name":"Lubuskie","plug_name":"RMF MAXX Lubuskie","stream":"https://rs102-krk.rmfstream.pl/rmf_maxxx_zgr","playlist":"getNowPlayingGrupaRMF(6);","station_schedule":"lubuskie","cover":"https://i.ibb.co/wZWkL29X/RMF-MAXX-logo.jpg"}]}
